split_interval.py
split_interval-0.1.0a1.dist-info/licenses/LICENSE
split_interval-0.1.0a1.dist-info/METADATA
split_interval-0.1.0a1.dist-info/WHEEL
split_interval-0.1.0a1.dist-info/top_level.txt
split_interval-0.1.0a1.dist-info/RECORD
