Metadata-Version: 2.4
Name: split-interval
Version: 0.1.0a1
Summary: A Python function that splits left-closed, right-open intervals into parts relative to a reference interval.
Author-email: Jifeng Wu <jifengwu2k@gmail.com>
License-Expression: MIT
Project-URL: Homepage, https://github.com/jifengwu2k/split-interval
Project-URL: Bug Tracker, https://github.com/jifengwu2k/split-interval/issues
Classifier: Programming Language :: Python :: 2
Classifier: Programming Language :: Python :: 3
Classifier: Operating System :: OS Independent
Requires-Python: >=2
License-File: LICENSE
Requires-Dist: typing; python_version < "3.5"
Dynamic: license-file
